matroid_database/__init__.py
matroid_database/_all/allr1n01.txt.xz
matroid_database/_all/allr1n02.txt.xz
matroid_database/_all/allr1n03.txt.xz
matroid_database/_all/allr1n04.txt.xz
matroid_database/_all/allr1n05.txt.xz
matroid_database/_all/allr1n06.txt.xz
matroid_database/_all/allr1n07.txt.xz
matroid_database/_all/allr1n08.txt.xz
matroid_database/_all/allr1n09.txt.xz
matroid_database/_all/allr1n10.txt.xz
matroid_database/_all/allr1n11.txt.xz
matroid_database/_all/allr1n12.txt.xz
matroid_database/_all/allr2n02.txt.xz
matroid_database/_all/allr2n03.txt.xz
matroid_database/_all/allr2n04.txt.xz
matroid_database/_all/allr2n05.txt.xz
matroid_database/_all/allr2n06.txt.xz
matroid_database/_all/allr2n07.txt.xz
matroid_database/_all/allr2n08.txt.xz
matroid_database/_all/allr2n09.txt.xz
matroid_database/_all/allr2n10.txt.xz
matroid_database/_all/allr2n11.txt.xz
matroid_database/_all/allr2n12.txt.xz
matroid_database/_all/allr3n03.txt.xz
matroid_database/_all/allr3n04.txt.xz
matroid_database/_all/allr3n05.txt.xz
matroid_database/_all/allr3n06.txt.xz
matroid_database/_all/allr3n07.txt.xz
matroid_database/_all/allr3n08.txt.xz
matroid_database/_all/allr3n09.txt.xz
matroid_database/_all/allr3n10.txt.xz
matroid_database/_all/allr3n11.txt.xz
matroid_database/_all/allr4n04.txt.xz
matroid_database/_all/allr4n05.txt.xz
matroid_database/_all/allr4n06.txt.xz
matroid_database/_all/allr4n07.txt.xz
matroid_database/_all/allr4n08.txt.xz
matroid_database/_all/allr4n09.txt.xz
matroid_database/_unorientable/unorientabler3n07.txt.xz
matroid_database/_unorientable/unorientabler3n08.txt.xz
matroid_database/_unorientable/unorientabler3n09.txt.xz
matroid_database/_unorientable/unorientabler3n10.txt.xz
matroid_database/_unorientable/unorientabler3n11.txt.xz
matroid_database/_unorientable/unorientabler4n07.txt.xz
matroid_database/_unorientable/unorientabler4n08.txt.xz
matroid_database/_unorientable/unorientabler4n09.txt.xz
matroid_database-0.3.dist-info/LICENSE
matroid_database-0.3.dist-info/METADATA
matroid_database-0.3.dist-info/WHEEL
matroid_database-0.3.dist-info/top_level.txt
matroid_database-0.3.dist-info/RECORD
