Metadata-Version: 2.1
Name: matroid-database
Version: 0.3
Summary: Python interface to matroid database
License: GNU GENERAL PUBLIC LICENSE
Project-URL: Homepage, https://github.com/gmou3/matroid-database
Project-URL: Documentation, https://github.com/gmou3/matroid-database/blob/main/README.rst
Project-URL: Repository, https://github.com/gmou3/matroid-database.git
Keywords: mathematics,combinatorics,matroids
Classifier: License :: OSI Approved :: GNU General Public License v3 or later (GPLv3+)
Classifier: Programming Language :: Python :: 3
Classifier: Topic :: Scientific/Engineering :: Mathematics
Classifier: Topic :: Software Development :: Libraries :: Python Modules
Requires-Python: >=3.9
License-File: LICENSE
